EDX/MADES_SOAP_API.py
EDX/__init__.py
EDX/_version.py
edx-0.0.17.dist-info/licenses/LICENSE
edx-0.0.17.dist-info/METADATA
edx-0.0.17.dist-info/WHEEL
edx-0.0.17.dist-info/top_level.txt
edx-0.0.17.dist-info/RECORD
