Metadata-Version: 2.4
Name: EDX
Version: 0.0.17
Summary: EDX MADES SOAP API implementation in python
Home-page: https://github.com/Haigutus/EDX
Author: Kristjan Vilgo
Author-email: kristjan.vilgo@gmail.com
License: MIT
Classifier: Programming Language :: Python :: 3
Classifier: License :: OSI Approved :: MIT License
Classifier: Operating System :: OS Independent
License-File: LICENSE
Requires-Dist: requests
Requires-Dist: zeep
Requires-Dist: urllib3
Requires-Dist: lxml
Dynamic: author
Dynamic: author-email
Dynamic: classifier
Dynamic: description
Dynamic: description-content-type
Dynamic: home-page
Dynamic: license
Dynamic: license-file
Dynamic: requires-dist
Dynamic: summary
